viacent_package/__init__.py
viacent_package/cli.py
viacent_package/count_unique_chars.py
viacent_package-0.1.6.dist-info/METADATA
viacent_package-0.1.6.dist-info/WHEEL
viacent_package-0.1.6.dist-info/entry_points.txt
viacent_package-0.1.6.dist-info/licenses/LICENSE
viacent_package-0.1.6.dist-info/RECORD
