Metadata-Version: 2.4
Name: viacent_package
Version: 0.1.6
Summary: A Python package for counting unique characters in strings and files.
Author-email: Oleksandr Khomiarchuk <akhomyarchuk@gmail.com>
License: MIT License
License-File: LICENSE
